uv2compdb/__init__.py
uv2compdb/__main__.py
uv2compdb/main.py
uv2compdb/parser.py
uv2compdb-0.3.0.dist-info/licenses/LICENSE
uv2compdb-0.3.0.dist-info/WHEEL
uv2compdb-0.3.0.dist-info/entry_points.txt
uv2compdb-0.3.0.dist-info/METADATA
uv2compdb-0.3.0.dist-info/RECORD
