Metadata-Version: 2.4
Name: uv2compdb
Version: 0.3.0
Summary: Generate Compilation Database by parse Keil µVision project
Keywords: keil,MDK,µVision,clangd,Compilation Database,compiled_commands.json
Author: xbin
Author-email: xbin <xbin.xu@qq.com>
License-Expression: MIT
License-File: LICENSE
Classifier: Development Status :: 4 - Beta
Classifier: Environment :: Console
Classifier: Intended Audience :: Developers
Classifier: License :: OSI Approved :: MIT License
Classifier: Operating System :: OS Independent
Classifier: Programming Language :: Python :: 3
Classifier: Topic :: Software Development :: Embedded Systems
Classifier: Topic :: Utilities
Requires-Python: >=3.8
Project-URL: Homepage, https://github.com/xbin-xu/uv2compdb
Project-URL: Issues, https://github.com/xbin-xu/uv2compdb/issues
